contrib/configuration_lifecycle.py
netbox_lifecycle/__init__.py
netbox_lifecycle/navigation.py
netbox_lifecycle/search.py
netbox_lifecycle/template_content.py
netbox_lifecycle/urls.py
netbox_lifecycle/api/__init__.py
netbox_lifecycle/api/serializers.py
netbox_lifecycle/api/urls.py
netbox_lifecycle/api/_serializers/__init__.py
netbox_lifecycle/api/_serializers/contract.py
netbox_lifecycle/api/_serializers/hardware.py
netbox_lifecycle/api/_serializers/license.py
netbox_lifecycle/api/_serializers/vendor.py
netbox_lifecycle/api/views/__init__.py
netbox_lifecycle/api/views/contract.py
netbox_lifecycle/api/views/hardware.py
netbox_lifecycle/api/views/license.py
netbox_lifecycle/constants/__init__.py
netbox_lifecycle/constants/contract.py
netbox_lifecycle/constants/hardware.py
netbox_lifecycle/filtersets/__init__.py
netbox_lifecycle/filtersets/contract.py
netbox_lifecycle/filtersets/hardware.py
netbox_lifecycle/filtersets/license.py
netbox_lifecycle/forms/__init__.py
netbox_lifecycle/forms/bulk_edit.py
netbox_lifecycle/forms/filtersets.py
netbox_lifecycle/forms/model_forms.py
netbox_lifecycle/graphql/__init__.py
netbox_lifecycle/graphql/filters.py
netbox_lifecycle/graphql/schema.py
netbox_lifecycle/graphql/types.py
netbox_lifecycle/migrations/0001_initial.py
netbox_lifecycle/migrations/0002_license_licenseassignment.py
netbox_lifecycle/migrations/0003_remove_supportcontract_devices_and_more.py
netbox_lifecycle/migrations/0004_supportcontractassignment_and_more.py
netbox_lifecycle/migrations/0005_remove_supportcontract_manufacturer_supportsku_and_more.py
netbox_lifecycle/migrations/0006_alter_supportcontractassignment_assigned_object_type.py
netbox_lifecycle/migrations/0007_alter_hardwarelifecycle_options_and_more.py
netbox_lifecycle/migrations/0008_alter_supportcontractassignment_contract_and_more.py
netbox_lifecycle/migrations/0009_alter_licenseassignment_device.py
netbox_lifecycle/migrations/0010_licenseassignment_quantity.py
netbox_lifecycle-1.1.7.dist-info/licenses/LICENSE
netbox_lifecycle-1.1.7.dist-info/METADATA
netbox_lifecycle-1.1.7.dist-info/WHEEL
netbox_lifecycle-1.1.7.dist-info/top_level.txt
netbox_lifecycle-1.1.7.dist-info/RECORD
