Metadata-Version: 2.4
Name: netbox-lifecycle
Version: 1.1.7
Summary: NetBox Support Contract and EOL/EOS management
Author-email: Daniel Sheppard <dans@dansheps.com>
Maintainer-email: Daniel Sheppard <dans@dansheps.com>
License:                                  Apache License
Project-URL: Documentation, https://github.com/dansheps/netbox-lifecycle/blob/main/README.md
Project-URL: Source, https://github.com/dansheps/netbox-lifecycle
Project-URL: Tracker, https://github.com/dansheps/netbox-lifecycle/issues
Keywords: netbox-plugin
Classifier: Programming Language :: Python :: 3
Requires-Python: >=3.12
License-File: LICENSE
Requires-Dist: django-polymorphic
Dynamic: license-file
